{
  "version": "7",
  "dialect": "postgresql",
  "entries": [
    {
      "idx": 0,
      "version": "7",
      "when": 1776797490680,
      "tag": "0000_flippant_ezekiel",
      "breakpoints": true
    },
    {
      "idx": 1,
      "version": "7",
      "when": 1776947522381,
      "tag": "0001_timescaledb_extension",
      "breakpoints": true
    },
    {
      "idx": 2,
      "version": "7",
      "when": 1776949569595,
      "tag": "0002_hypertable_revenue_events",
      "breakpoints": true
    },
    {
      "idx": 3,
      "version": "7",
      "when": 1776951385379,
      "tag": "0003_hypertable_credit_ledger",
      "breakpoints": true
    },
    {
      "idx": 4,
      "version": "7",
      "when": 1776952380764,
      "tag": "0004_hypertable_outgoing_webhooks",
      "breakpoints": true
    },
    {
      "idx": 5,
      "version": "7",
      "when": 1776954938603,
      "tag": "0005_cagg_daily_mrr",
      "breakpoints": true
    },
    {
      "idx": 6,
      "version": "7",
      "when": 1776955535301,
      "tag": "0006_compression_policies",
      "breakpoints": true
    },
    {
      "idx": 7,
      "version": "7",
      "when": 1776955883796,
      "tag": "0007_retention_policies",
      "breakpoints": true
    },
    {
      "idx": 8,
      "version": "7",
      "when": 1776965592853,
      "tag": "0008_experiment_assignments_hash_version",
      "breakpoints": true
    },
    {
      "idx": 9,
      "version": "7",
      "when": 1777334400000,
      "tag": "0009_exposure_events",
      "breakpoints": true
    },
    {
      "idx": 10,
      "version": "7",
      "when": 1777420800000,
      "tag": "0010_postgres_publication",
      "breakpoints": true
    },
    {
      "idx": 11,
      "version": "7",
      "when": 1777507200000,
      "tag": "0011_drop_publication",
      "breakpoints": true
    },
    {
      "idx": 12,
      "version": "7",
      "when": 1777510800000,
      "tag": "0012_drop_exposure_events",
      "breakpoints": true
    },
    {
      "idx": 13,
      "version": "7",
      "when": 1777514400000,
      "tag": "0013_outbox_events",
      "breakpoints": true
    },
    {
      "idx": 14,
      "version": "7",
      "when": 1777681800000,
      "tag": "0014_drop_daily_mrr_cagg",
      "breakpoints": true
    },
    {
      "idx": 15,
      "version": "7",
      "when": 1777681900000,
      "tag": "0015_partition_revenue_events",
      "breakpoints": true
    },
    {
      "idx": 16,
      "version": "7",
      "when": 1777682000000,
      "tag": "0016_partition_credit_ledger",
      "breakpoints": true
    },
    {
      "idx": 17,
      "version": "7",
      "when": 1777682100000,
      "tag": "0017_partition_outgoing_webhooks",
      "breakpoints": true
    },
    {
      "idx": 18,
      "version": "7",
      "when": 1777682200000,
      "tag": "0015a_drop_revenue_events_legacy",
      "breakpoints": true
    },
    {
      "idx": 19,
      "version": "7",
      "when": 1777682300000,
      "tag": "0016a_drop_credit_ledger_legacy",
      "breakpoints": true
    },
    {
      "idx": 20,
      "version": "7",
      "when": 1777682400000,
      "tag": "0017a_drop_outgoing_webhooks_legacy",
      "breakpoints": true
    },
    {
      "idx": 21,
      "version": "7",
      "when": 1777682500000,
      "tag": "0018_drop_timescaledb_extension",
      "breakpoints": true
    },
    {
      "idx": 22,
      "version": "7",
      "when": 1777682600000,
      "tag": "0019_install_pg_partman",
      "breakpoints": true
    },
    {
      "idx": 23,
      "version": "7",
      "when": 1777881637539,
      "tag": "0023_audit_logs_project_set_null",
      "breakpoints": true
    }
  ]
}